datatableview_advanced_search/__init__.py
datatableview_advanced_search/datatables.py
datatableview_advanced_search/forms.py
datatableview_advanced_search/lexer.py
datatableview_advanced_search/models.py
datatableview_advanced_search/parser.py
datatableview_advanced_search/parsetab.py
datatableview_advanced_search/urls.py
datatableview_advanced_search/utils.py
datatableview_advanced_search/views.py
datatableview_advanced_search/static/css/datatableview_advanced_search.css
datatableview_advanced_search/static/css/datatableview_advanced_search.min.css
datatableview_advanced_search/static/js/datatableview_advanced_search.js
datatableview_advanced_search/static/js/datatableview_advanced_search.min.js
datatableview_advanced_search/templates/datatableview_advanced_search/help_model.html
datatableview_advanced_search-1.2.1.dist-info/LICENSE.txt
datatableview_advanced_search-1.2.1.dist-info/METADATA
datatableview_advanced_search-1.2.1.dist-info/WHEEL
datatableview_advanced_search-1.2.1.dist-info/top_level.txt
datatableview_advanced_search-1.2.1.dist-info/RECORD
