Metadata-Version: 2.1
Name: datatableview-advanced-search
Version: 1.2.1
Summary: Allows a user to use logical operators in the datatableview search window
Home-page: https://github.com/icmanage/django-datatable-view-adv-query
Author: Steven Klass
Author-email: sklass@icmanage.com
License: UNKNOWN
Download-URL: https://github.com/icmanage/django-datatable-view-adv-query/archive/1.2.1.tar.gz
Project-URL: Bug Reports, https://github.com/icmanage/django-datatable-view-adv-query/issues
Project-URL: Say Thanks!, http://saythanks.io/to/rh0dium
Project-URL: Source, https://github.com/icmanage/django-datatable-view-adv-query
Keywords: django datatableview
Platform: UNKNOWN
Classifier: Development Status :: 4 - Beta
Classifier: Environment :: Web Environment
Classifier: Framework :: Django
Classifier: License :: OSI Approved :: MIT License
Classifier: Programming Language :: Python :: 3
Classifier: Programming Language :: Python :: 3.7
Classifier: Programming Language :: Python :: 3.8
Classifier: Programming Language :: Python :: 3.9
License-File: LICENSE.txt
Requires-Dist: django (<4,>=3)
Requires-Dist: django-datatable-view
Requires-Dist: ply (>=3.11)
